umapi_cli/__init__.py
umapi_cli/action_queue.py
umapi_cli/cli.py
umapi_cli/client.py
umapi_cli/config.py
umapi_cli/formatter.py
umapi_cli/log.py
umapi_cli/version.py
umapi_cli-2.2.0.dist-info/LICENSE
umapi_cli-2.2.0.dist-info/METADATA
umapi_cli-2.2.0.dist-info/WHEEL
umapi_cli-2.2.0.dist-info/entry_points.txt
umapi_cli-2.2.0.dist-info/RECORD
