Metadata-Version: 2.1
Name: umapi-cli
Version: 2.2.0
Summary: User Management API CLI Tool
Home-page: https://github.com/adobe/umapi-cli/
License: Apache 2.0
Author: Andrew Dorton
Author-email: adorton@adobe.com
Requires-Python: >=3.9,<4.0
Classifier: License :: Other/Proprietary License
Classifier: Programming Language :: Python :: 3
Classifier: Programming Language :: Python :: 3.9
Classifier: Programming Language :: Python :: 3.10
Classifier: Programming Language :: Python :: 3.11
Requires-Dist: click (>=8.0,<9.0)
Requires-Dist: python-dotenv (>=1.0.0,<2.0.0)
Requires-Dist: schema (>=0.7.5,<0.8.0)
Requires-Dist: umapi-client (>=3.0,<4.0)
Project-URL: Repository, https://github.com/adobe/umapi-cli/
